[
  {
    "route": {
      "timestampStart": "2016-01-16T16:10:39.551Z",
      "timestampStop": "2016-01-16T16:35:39.551Z",
      "routeDistance": "30",
      "routeDuration": "25",
      "drivenRoute": [
        {
          "gpsLatitude": "48.764409799999996",
          "gpsLongitude": "9.164410499999999"
        },
        {
          "gpsLatitude": "48.764409799999996",
          "gpsLongitude": "9.164410499999999"
        }
      ]
    },
    "ecoScoreAverage": "52",
    "ecoScoreDetails": {
      "accelaration": "45",
      "breaking": "33",
      "driving": "17"
    },
    "speedfenceAlerts": "3",
    "geofenceAlerts": "false",
    "espAlerts": "0",
    "kickdowns": "1",
    "fullBreakings": "4",
    "fuelAverage": "9",
    "userId": "tvetter",
    "vehicleId": "WDD1760121J350758"
  }
]
